pyvalem/__init__.py
pyvalem/_data_atomic_weights.txt
pyvalem/_data_isotope_masses.txt
pyvalem/_special_cases.py
pyvalem/_utils.py
pyvalem/atom_data.py
pyvalem/formula.py
pyvalem/reaction.py
pyvalem/stateful_species.py
pyvalem/states/J1J2_coupling.py
pyvalem/states/J1K_LK_coupling.py
pyvalem/states/__init__.py
pyvalem/states/_base_state.py
pyvalem/states/_state_parser.py
pyvalem/states/atomic_configuration.py
pyvalem/states/atomic_term_symbol.py
pyvalem/states/compound_LS_coupling.py
pyvalem/states/diatomic_molecular_configuration.py
pyvalem/states/generic_excited_state.py
pyvalem/states/key_value_pair.py
pyvalem/states/molecular_term_symbol.py
pyvalem/states/racah_symbol.py
pyvalem/states/rotational_state.py
pyvalem/states/vibrational_state.py
pyvalem-2.8.0.dist-info/LICENSE
pyvalem-2.8.0.dist-info/METADATA
pyvalem-2.8.0.dist-info/WHEEL
pyvalem-2.8.0.dist-info/top_level.txt
pyvalem-2.8.0.dist-info/RECORD
