Metadata-Version: 2.2
Name: pyvalem
Version: 2.8.0
Summary: A package for managing simple chemical species and states
Home-page: https://github.com/xnx/pyvalem
Author: Christian Hill
Author-email: ch.hill@iaea.org
Project-URL: Bug Reports, https://github.com/xnx/pyvalem/issues
Keywords: chemistry,formula,species,state,reaction
Classifier: Development Status :: 4 - Beta
Classifier: Intended Audience :: Science/Research
Classifier: Topic :: Scientific/Engineering :: Chemistry
Classifier: Topic :: Scientific/Engineering :: Physics
Classifier: License :: OSI Approved :: GNU General Public License v3 (GPLv3)
Classifier: Programming Language :: Python :: 3
Classifier: Programming Language :: Python :: 3.6
Classifier: Programming Language :: Python :: 3.7
Classifier: Programming Language :: Python :: 3.8
Classifier: Programming Language :: Python :: 3.9
Classifier: Programming Language :: Python :: 3.10
Classifier: Programming Language :: Python :: 3.11
Classifier: Programming Language :: Python :: 3.12
Classifier: Programming Language :: Python :: 3.13
Classifier: Programming Language :: Python :: 3 :: Only
Classifier: Operating System :: OS Independent
Requires-Python: >=3.6
License-File: LICENSE
Requires-Dist: pyparsing>=2.3
Requires-Dist: importlib-resources>=1.0; python_version < "3.7.0"
Provides-Extra: dev
Requires-Dist: black; extra == "dev"
Requires-Dist: pytest-cov; extra == "dev"
Requires-Dist: tox; extra == "dev"
Requires-Dist: ipython; extra == "dev"
Requires-Dist: sphinx; extra == "dev"
Dynamic: author
Dynamic: author-email
Dynamic: classifier
Dynamic: description
Dynamic: description-content-type
Dynamic: home-page
Dynamic: keywords
Dynamic: project-url
Dynamic: provides-extra
Dynamic: requires-dist
Dynamic: requires-python
Dynamic: summary
